README.rst
setup.cfg
setup.py
django_js_routing/__init__.py
django_js_routing/admin.py
django_js_routing/models.py
django_js_routing/tests.py
django_js_routing/urls.py
django_js_routing/utils.py
django_js_routing/views.py
django_js_routing.egg-info/PKG-INFO
django_js_routing.egg-info/SOURCES.txt
django_js_routing.egg-info/dependency_links.txt
django_js_routing.egg-info/top_level.txt