Metadata-Version: 1.1
Name: django-js-routing
Version: 1.0.4
Summary: Expose your Django routes to JavaScript
Home-page: https://github.com/magdkudama/django-js-routing
Author: Magd Kudama
Author-email: magdkudama@gmail.com
License: MIT
Keywords: django,routing,js
Platform: UNKNOWN
Classifier: Development Status :: 4 - Beta
Classifier: Intended Audience :: Developers
Classifier: License :: OSI Approved :: MIT License
Classifier: Programming Language :: Python
Classifier: Operating System :: OS Independent
Classifier: Topic :: Software Development
Classifier: Topic :: Utilities
Classifier: Environment :: Web Environment
Classifier: Framework :: Django
